MANIFEST.in
README.md
license.txt
setup.py
CyberSource/__init__.py
CyberSource/api_client.py
CyberSource/configuration.py
CyberSource/rest.py
CyberSource/api/__init__.py
CyberSource/api/bank_account_validation_api.py
CyberSource/api/batch_upload_with_mtls_api.py
CyberSource/api/batches_api.py
CyberSource/api/billing_agreements_api.py
CyberSource/api/bin_lookup_api.py
CyberSource/api/capture_api.py
CyberSource/api/chargeback_details_api.py
CyberSource/api/chargeback_summaries_api.py
CyberSource/api/conversion_details_api.py
CyberSource/api/create_new_webhooks_api.py
CyberSource/api/credit_api.py
CyberSource/api/customer_api.py
CyberSource/api/customer_payment_instrument_api.py
CyberSource/api/customer_shipping_address_api.py
CyberSource/api/decision_manager_api.py
CyberSource/api/device_de_association_api.py
CyberSource/api/device_search_api.py
CyberSource/api/download_dtd_api.py
CyberSource/api/download_xsd_api.py
CyberSource/api/emv_tag_details_api.py
CyberSource/api/flex_api_api.py
CyberSource/api/instrument_identifier_api.py
CyberSource/api/interchange_clearing_level_details_api.py
CyberSource/api/invoice_settings_api.py
CyberSource/api/invoices_api.py
CyberSource/api/manage_webhooks_api.py
CyberSource/api/merchant_boarding_api.py
CyberSource/api/merchant_defined_fields_api.py
CyberSource/api/microform_integration_api.py
CyberSource/api/net_fundings_api.py
CyberSource/api/notification_of_changes_api.py
CyberSource/api/o_auth_api.py
CyberSource/api/offers_api.py
CyberSource/api/orders_api.py
CyberSource/api/payer_authentication_api.py
CyberSource/api/payment_batch_summaries_api.py
CyberSource/api/payment_instrument_api.py
CyberSource/api/payment_links_api.py
CyberSource/api/payment_tokens_api.py
CyberSource/api/payments_api.py
CyberSource/api/payouts_api.py
CyberSource/api/plans_api.py
CyberSource/api/purchase_and_refund_details_api.py
CyberSource/api/push_funds_api.py
CyberSource/api/refund_api.py
CyberSource/api/report_definitions_api.py
cybersource_rest_client_python.egg-info/PKG-INFO
cybersource_rest_client_python.egg-info/SOURCES.txt
cybersource_rest_client_python.egg-info/dependency_links.txt
cybersource_rest_client_python.egg-info/requires.txt
cybersource_rest_client_python.egg-info/top_level.txt