Metadata-Version: 2.2
Name: cybersource-rest-client-python
Version: 0.0.71
Summary: SDK for the CyberSource REST API
Home-page: https://github.com/CyberSource/cybersource-rest-client-python
Author-email: developer@cybersource.com
Keywords: Payments API,CyberSource
Classifier: Intended Audience :: Developers
Classifier: Operating System :: OS Independent
Classifier: Programming Language :: Python
Classifier: Programming Language :: Python :: 2.7
Classifier: Programming Language :: Python :: 3
Classifier: Programming Language :: Python :: 3.5
Classifier: Programming Language :: Python :: 3.6
Classifier: Programming Language :: Python :: 3.7
Classifier: Programming Language :: Python :: 3.8
Classifier: Topic :: Software Development :: Libraries :: Python Modules
License-File: license.txt
Requires-Dist: certifi
Requires-Dist: pycryptodome
Requires-Dist: PyJWT<2.10.0
Requires-Dist: DateTime
Requires-Dist: setuptools
Requires-Dist: six
Requires-Dist: urllib3-future
Requires-Dist: jwcrypto
Requires-Dist: cryptography
Requires-Dist: pgpy
Dynamic: author-email
Dynamic: classifier
Dynamic: description
Dynamic: home-page
Dynamic: keywords
Dynamic: requires-dist
Dynamic: summary
